analytics_mcp/__init__.py
analytics_mcp/coordinator.py
analytics_mcp/server.py
analytics_mcp/tools/__init__.py
analytics_mcp/tools/utils.py
analytics_mcp/tools/admin/info.py
analytics_mcp/tools/reporting/__init__.py
analytics_mcp/tools/reporting/core.py
analytics_mcp/tools/reporting/metadata.py
analytics_mcp/tools/reporting/realtime.py
google_analytics_mcp_python-0.1.3.dist-info/licenses/LICENSE
google_analytics_mcp_python-0.1.3.dist-info/METADATA
google_analytics_mcp_python-0.1.3.dist-info/WHEEL
google_analytics_mcp_python-0.1.3.dist-info/entry_points.txt
google_analytics_mcp_python-0.1.3.dist-info/top_level.txt
google_analytics_mcp_python-0.1.3.dist-info/RECORD
