Metadata-Version: 2.4
Name: google-analytics-mcp-python
Version: 0.1.3
Summary: MCP Server for Google Analytics API access
Author-email: Locomotive Agency <cloud@locomotive.agency>, Josh Radcliff <jradcliff@users.noreply.github.com>, Matt Landers <matt-landers@users.noreply.github.com>
License-Expression: Apache-2.0
Project-URL: homepage, https://github.com/locomotive-agency/google-analytics-mcp
Project-URL: repository, https://github.com/locomotive-agency/google-analytics-mcp
Project-URL: issues, https://github.com/locomotive-agency/google-analytics-mcp/issues
Keywords: mcp,google-analytics,ai,tools,ga4,analytics
Classifier: Development Status :: 4 - Beta
Classifier: Intended Audience :: Developers
Classifier: Programming Language :: Python :: 3
Classifier: Programming Language :: Python :: 3.10
Classifier: Programming Language :: Python :: 3.11
Classifier: Programming Language :: Python :: 3.12
Classifier: Programming Language :: Python :: 3.13
Classifier: Operating System :: OS Independent
Classifier: Topic :: Software Development :: Libraries :: Python Modules
Classifier: Topic :: Internet :: WWW/HTTP :: Indexing/Search
Requires-Python: >=3.10
License-File: LICENSE
Requires-Dist: google-analytics-data==0.18.19
Requires-Dist: google-analytics-admin==0.25.0
Requires-Dist: google-auth~=2.40
Requires-Dist: mcp[cli]>=1.2.0
Requires-Dist: httpx>=0.28.1
Provides-Extra: dev
Requires-Dist: black; extra == "dev"
Requires-Dist: nox<2026,>=2025.5.1; extra == "dev"
Dynamic: license-file
